Metadata-Version: 2.4
Name: mseep-screenmonitormcp-v2
Version: 2.0.13
Summary: A revolutionary Model Context Protocol (MCP) server that gives AI real-time vision capabilities and enhanced UI intelligence power
Author-email: mseep <support@skydeck.ai>
Maintainer-email: inkbytefo <inkbytefo@gmail.com>
License: MIT
Project-URL: Homepage, https://github.com/inkbytefo/ScreenMonitorMCP
Project-URL: Repository, https://github.com/inkbytefo/ScreenMonitorMCP
Project-URL: Documentation, https://github.com/inkbytefo/ScreenMonitorMCP/blob/main/README.md
Project-URL: Bug Tracker, https://github.com/inkbytefo/ScreenMonitorMCP/issues
Project-URL: Changelog, https://github.com/inkbytefo/ScreenMonitorMCP/blob/main/CHANGELOG.md
Keywords: mcp,screen,monitor,capture,ai,vision,automation
Classifier: Development Status :: 4 - Beta
Classifier: Intended Audience :: Developers
Classifier: License :: OSI Approved :: MIT License
Classifier: Operating System :: OS Independent
Classifier: Programming Language :: Python :: 3
Classifier: Programming Language :: Python :: 3.8
Classifier: Programming Language :: Python :: 3.9
Classifier: Programming Language :: Python :: 3.10
Classifier: Programming Language :: Python :: 3.11
Classifier: Programming Language :: Python :: 3.12
Classifier: Topic :: Software Development :: Libraries :: Python Modules
Classifier: Topic :: System :: Monitoring
Classifier: Topic :: Multimedia :: Graphics :: Capture :: Screen Capture
Requires-Python: >=3.8
License-File: LICENSE
Requires-Dist: fastapi>=0.104.0
Requires-Dist: uvicorn[standard]>=0.24.0
Requires-Dist: mss>=9.0.1
Requires-Dist: Pillow>=10.0.0
Requires-Dist: openai>=1.3.0
Requires-Dist: psutil>=5.9.0
Requires-Dist: python-dotenv>=1.0.0
Requires-Dist: pydantic>=2.0.0
Requires-Dist: structlog>=23.1.0
Requires-Dist: aiosqlite>=0.19.0
Requires-Dist: mcp>=1.0.0
Provides-Extra: dev
Requires-Dist: pytest>=7.0.0; extra == "dev"
Requires-Dist: pytest-asyncio>=0.21.0; extra == "dev"
Requires-Dist: pytest-cov>=4.0.0; extra == "dev"
Requires-Dist: black>=23.0.0; extra == "dev"
Requires-Dist: isort>=5.12.0; extra == "dev"
Requires-Dist: flake8>=6.0.0; extra == "dev"
Requires-Dist: mypy>=1.5.0; extra == "dev"
Requires-Dist: pre-commit>=3.0.0; extra == "dev"
Provides-Extra: testing
Requires-Dist: pytest>=7.0.0; extra == "testing"
Requires-Dist: pytest-asyncio>=0.21.0; extra == "testing"
Requires-Dist: pytest-cov>=4.0.0; extra == "testing"
Requires-Dist: httpx>=0.24.0; extra == "testing"
Provides-Extra: docs
Requires-Dist: sphinx>=7.0.0; extra == "docs"
Requires-Dist: sphinx-rtd-theme>=1.3.0; extra == "docs"
Requires-Dist: myst-parser>=2.0.0; extra == "docs"
Dynamic: license-file
